LICENSE.txt
MANIFEST.in
README.md
setup.py
yamlpy/__init__.py
yamlpy/yaml_py.py
yamlpy.egg-info/PKG-INFO
yamlpy.egg-info/SOURCES.txt
yamlpy.egg-info/dependency_links.txt
yamlpy.egg-info/entry_points.txt
yamlpy.egg-info/not-zip-safe
yamlpy.egg-info/requires.txt
yamlpy.egg-info/top_level.txt
yamlpy/demo/.dockerignore
yamlpy/demo/.gitignore
yamlpy/demo/Dockerfile
yamlpy/demo/Jenkinsfile
yamlpy/demo/README.md
yamlpy/demo/conftest.py
yamlpy/demo/pytest.ini
yamlpy/demo/requirements.txt
yamlpy/demo/case/__init__.py
yamlpy/demo/case/demo_test.py
yamlpy/demo/resource/demo_one.yaml
yamlpy/demo/resource/demo_three.yaml
yamlpy/demo/resource/demo_two.yaml
yamlpy/demo/setting/__init__.py
yamlpy/demo/setting/project_config.py
yamlpy/demo/tool/__init__.py
yamlpy/demo/tool/connect_influx.py
yamlpy/demo/tool/connect_mongo.py
yamlpy/demo/tool/connect_mysql.py
yamlpy/demo/tool/connect_postgresql.py
yamlpy/demo/tool/create_random.py
yamlpy/demo/tool/data_type_conversion.py
yamlpy/demo/tool/dingtalk_robot.py
yamlpy/demo/tool/export_test_case.py
yamlpy/demo/tool/feishu_robot.py
yamlpy/demo/tool/function_assistant.py
yamlpy/demo/tool/read_write_json.py
yamlpy/demo/tool/read_write_yaml.py
yamlpy/demo/tool/wechat_robot.py